proglang_select_local.py
proglang_select_local_python.py
proglang_select_transform.py
proglang_select_transform_python.py
dpk_proglang_select_transform_python-0.2.0.dist-info/METADATA
dpk_proglang_select_transform_python-0.2.0.dist-info/WHEEL
dpk_proglang_select_transform_python-0.2.0.dist-info/top_level.txt
dpk_proglang_select_transform_python-0.2.0.dist-info/RECORD
